msds_tdm/Hazard_list_detailed.xlsx
msds_tdm/__init__.py
msds_tdm/sigma_aldrich.py
tests/__init__.py
tests/test_msds.py
msds_tdm-1.0.3.dist-info/LICENSE
msds_tdm-1.0.3.dist-info/METADATA
msds_tdm-1.0.3.dist-info/WHEEL
msds_tdm-1.0.3.dist-info/top_level.txt
msds_tdm-1.0.3.dist-info/RECORD
