Metadata-Version: 2.1
Name: msds-tdm
Version: 1.0.3
Summary: MSDS Package
Home-page: https://github.com/sawlachintan/msds-library
Author: Soutick Saha, Chintan Sawla
Author-email: soutick2010@gmail.com, sawlachintan@gmail.com
License: UNKNOWN
Project-URL: Bug Tracker, https://github.com/sawlachintan/msds-library/issues
Platform: UNKNOWN
Classifier: Programming Language :: Python :: 3
Classifier: License :: OSI Approved :: MIT License
Classifier: Operating System :: OS Independent
Requires-Python: >=3.6
License-File: LICENSE
Requires-Dist: pandas (==1.2.4)
Requires-Dist: pdfplumber (==0.6.0)
Requires-Dist: openpyxl
